{
  "updatedAt": "2026-04-22T06:25:42.223Z",
  "entries": [
    {
      "href": "https://www.mof.gov.cn/gp/xxgkml/jdjcj/202604/t20260414_3987540.htm",
      "title": "财政部行政处罚决定书（财监法〔2026〕90号）",
      "aiAnalysis": "**【涉及准则】**：《企业会计准则第14号——收入》\n**【违规点】**：\n1、开展不具有商业实质的贸易业务，虚增营业收入、营业成本和利润\n2、作为代理人身份从事贸易业务，未按净额法确认收入，错误采用总额法核算，导致多计收入和成本"
    },
    {
      "href": "https://www.mof.gov.cn/gp/xxgkml/jdjcj/202603/t20260324_3986039.htm",
      "title": "财政部行政处罚决定书（财监法〔2026〕61号）",
      "aiAnalysis": "**【涉及准则】**：《企业会计准则第8号——资产减值》、《资产评估准则——基本准则》、《资产评估执业准则——资产评估方法》\n**【违规点】**：\n1、资产减值测试评估时选用与评估目的不符的价值类型，未按规定在评估结果低于账面价值时采用其他方法进一步验证\n2、未采用规定的方法计算资产可收回金额，选用的现金流量口径不符合资产减值测试的要求\n3、未来资本性支出计算错误，导致评估结论出现重大偏差"
    },
    {
      "href": "https://www.mof.gov.cn/gp/xxgkml/jdjcj/202603/t20260324_3986037.htm",
      "title": "财政部行政处罚决定书（财监法〔2026〕60号）",
      "aiAnalysis": "**【涉及准则】**：《企业会计准则第8号——资产减值》、《资产评估准则——基本准则》\n**【违规点】**：\n1、计算资产未来现金流量时未扣除对应的固定资产投资支出，导致评估结论高估\n2、未区分无形资产与其他资产的收益贡献，将项目全部预期收益归为无形资产收益，导致无形资产价值评估不准确"
    },
    {
      "href": "https://www.mof.gov.cn/gp/xxgkml/jdjcj/202603/t20260324_3986035.htm",
      "title": "财政部行政处罚决定书（财监法〔2026〕59号）",
      "aiAnalysis": "**【涉及准则】**：《企业会计准则第8号——资产减值》、《资产评估准则——基本准则》\n**【违规点】**：\n1、计算资产未来现金流量时未扣除对应的固定资产投资支出，导致评估结论高估\n2、未区分无形资产与其他资产的收益贡献，将项目全部预期收益归为无形资产收益，导致无形资产价值评估不准确"
    },
    {
      "href": "https://www.mof.gov.cn/gp/xxgkml/jdjcj/202603/t20260316_3985412.htm",
      "title": "财政部行政处罚决定书（财监法〔2026〕12号）",
      "aiAnalysis": "**【涉及准则】**：《资产评估准则——基本准则》、《资产评估职业道德准则——基本准则》\n**【违规点】**：\n1、评定估算形成结论不恰当，测算资产组预计未来现金流量现值时，未依据特许经营合同约定的有效期限确定收益期，错误采用永续期作为收益期，导致评估结论偏差\n2、重要评估资料缺失，资产评估档案中无特许经营合同、管道设计供气量等影响评估结论的关键资料，违反评估资料收集要求"
    },
    {
      "href": "https://www.mof.gov.cn/gp/xxgkml/jdjcj/202603/t20260316_3985411.htm",
      "title": "财政部行政处罚决定书（财监法〔2026〕11号）",
      "aiAnalysis": "**【涉及准则】**：《资产评估准则——基本准则》、《企业会计准则第8号——资产减值》\n**【违规点】**：\n1、测算资产组预计未来现金流量现值时，未依据特许经营合同约定的有效期限确定收益期，错误采用永续期作为收益期，导致评估结论偏差\n2、资产评估档案中缺失特许经营合同、资产设计参数等影响评估结论的关键资料，违反评估资料收集的完整性要求"
    },
    {
      "href": "https://www.mof.gov.cn/gp/xxgkml/jdjcj/202603/t20260316_3985402.htm",
      "title": "财政部行政处罚决定书（财监法〔2026〕7号）",
      "aiAnalysis": "**【涉及准则】**：《企业会计准则第8号——资产减值》、《资产评估准则——基本准则》、《资产评估执业准则——资产评估方法》、《中华人民共和国资产评估法》\n**【违规点】**：\n1、采用市场法评估时选取的可比公司与被评估单位业务类型差异大，不具有可比性\n2、在具备采用多种评估方法条件的情况下，仅采用市场法一种方法进行评估，理由不成立\n3、采用市场法评估时，未调查可比公司的项目投资收益分配方式，也未将其作为关键可比条件进行修正\n4、计算股权折扣率时，评估假设与公司章程约定不一致，确定的股权折扣率不合理\n5、重要资产评估档案缺失，无占资产总额比例极高的交易性金融资产的产权证明文件及权属核实记录"
    },
    {
      "href": "https://www.mof.gov.cn/gp/xxgkml/jdjcj/202603/t20260316_3985399.htm",
      "title": "财政部行政处罚决定书（财监法〔2026〕4号）",
      "aiAnalysis": "**【涉及准则】**：《资产评估执业准则——机器设备》、《企业会计准则第4号——固定资产》\n**【违规点】**：\n1、采用收益法评估机器设备时，预测期内折旧合计金额明显高于预测期内资本性支出总额与评估基准日机器设备账面净值之和，且未提供合理解释，评估逻辑不符合准则要求"
    },
    {
      "href": "https://www.mof.gov.cn/gp/xxgkml/jdjcj/202603/t20260316_3985397.htm",
      "title": "财政部行政处罚决定书（财监法〔2026〕3号）",
      "aiAnalysis": "**【涉及准则】**：《企业会计准则第8号——资产减值》、《资产评估准则——基本准则》、《资产评估执业准则——资产评估方法》\n**【违规点】**：\n1、未与相关方沟通，擅自调整关键评估参数，且调整后评估结论与原结论完全一致，评估过程缺乏合理性"
    },
    {
      "href": "https://www.mof.gov.cn/gp/xxgkml/jdjcj/202603/t20260316_3985396.htm",
      "title": "财政部行政处罚决定书（财监法〔2026〕2号）",
      "aiAnalysis": "**【涉及准则】**：《资产评估执业准则——机器设备》、《监管规则适用指引——评估类第2号》\n**【违规点】**：\n1、在未与委托方及相关方沟通的情况下，擅自调整关键评估参数，且调整后评估结论与原参数下的评估结果一致，评估程序存在瑕疵\n2、采用收益法评估机器设备时，预测期内折旧合计金额明显高于预测期内资本性支出总额与评估基准日机器设备账面净值之和，且未提供合理解释，评估逻辑不符合准则要求"
    },
    {
      "href": "https://www.mof.gov.cn/gp/xxgkml/jdjcj/202603/t20260316_3985394.htm",
      "title": "财政部行政处罚决定书（财监法〔2026〕1号）",
      "aiAnalysis": "**【涉及准则】**：《企业会计准则第8号——资产减值》、《资产评估准则——基本准则》、《资产评估执业准则——资产评估方法》\n**【违规点】**：\n1、未与相关方沟通，擅自调整关键评估参数，且调整后评估结论与原结论完全一致，评估过程缺乏合理性\n2、采用收益法评估时，预测期内机器设备折旧合计金额明显高于预测期内资本性支出总额与评估基准日机器设备账面净值之和，且无合理解释，参数设定不符合资产运营逻辑"
    }
  ]
}